<!--
  ~ Copyright (C) 2007-2019 Crafter Software Corporation. All Rights Reserved.
  ~
  ~ This program is free software: you can redistribute it and/or modify
  ~ it under the terms of the GNU General Public License as published by
  ~ the Free Software Foundation, either version 3 of the License, or
  ~ (at your option) any later version.
  ~
  ~ This program is distributed in the hope that it will be useful,
  ~ but WITHOUT ANY WARRANTY; without even the implied warranty of
  ~ MERCHANTABILITY or FITNESS FOR A PARTICULAR PURPOSE.  See the
  ~ GNU General Public License for more details.
  ~
  ~ You should have received a copy of the GNU General Public License
  ~ along with this program.  If not, see <http://www.gnu.org/licenses/>.
  -->

<form>
	<title>Component - Header</title>
	<description></description>
	<objectType>component</objectType>
	<content-type>/component/header</content-type>
	<imageThumbnail>component-header.png</imageThumbnail>
    <quickCreate>false</quickCreate>
    <quickCreatePath></quickCreatePath>
	<properties>		<property>
			<name>display-template</name>
			<label>Display Template</label>
			<value>/templates/web/components/header.ftl</value>
			<type>template</type>
		</property>
		<property>
			<name>no-template-required</name>
			<label>No Template Required</label>
			<value></value>
			<type>boolean</type>
		</property>
		<property>
			<name>merge-strategy</name>
			<label>Merge Strategy</label>
			<value>inherit-levels</value>
			<type>string</type>
		</property>
	</properties>
	<sections>		<section>
			<title>Component - Header Properties</title>
			<description></description>
			<defaultOpen>true</defaultOpen>
			<fields>
				<field>
					<type>file-name</type>
					<id>file-name</id>
					<iceId></iceId>
					<title>Component ID</title>
					<description></description>
					<defaultValue></defaultValue>
					<help></help>
					<properties>
						<property>
							<name>size</name>
							<value>50</value>
							<type>int</type>
						</property>
						<property>
							<name>maxlength</name>
							<value>50</value>
							<type>int</type>
						</property>
						<property>
							<name>readonly</name>
							<value></value>
							<type>boolean</type>
						</property>
					</properties>
					<constraints>
					</constraints>
				</field>
				<field>
					<type>input</type>
					<id>internal-name</id>
					<iceId></iceId>
					<title>Internal Name</title>
					<description></description>
					<defaultValue></defaultValue>
					<help></help>
					<properties>
						<property>
							<name>size</name>
							<value>50</value>
							<type>int</type>
						</property>
						<property>
							<name>maxlength</name>
							<value>50</value>
							<type>int</type>
						</property>
					</properties>
					<constraints>
						<constraint>
							<name>required</name>
							<value><![CDATA[true]]></value>
							<type>boolean</type>
						</constraint>
					</constraints>
				</field>
				<field>
					<type>checkbox</type>
					<id>disabled</id>
					<iceId></iceId>
					<title>Disable Component</title>
					<description></description>
					<defaultValue></defaultValue>
					<help></help>
					<properties>
						<property>
							<name>readonly</name>
							<value></value>
							<type>boolean</type>
						</property>
					</properties>
					<constraints>
						<constraint>
							<name>required</name>
							<value><![CDATA[]]></value>
							<type>boolean</type>
						</constraint>
					</constraints>
				</field>
			</fields>
		</section>
		<section>
			<title>Business Name and Logo</title>
			<description></description>
			<defaultOpen>true</defaultOpen>
			<fields>
				<field>
					<type>image-picker</type>
					<id>logo_s</id>
					<iceId>header</iceId>
					<title>Logo</title>
					<description></description>
					<defaultValue></defaultValue>
					<help></help>
					<properties>
						<property>
							<name>width</name>
							<value>{ &quot;exact&quot;:&quot;&quot;, &quot;min&quot;:&quot;&quot;, &quot;max&quot;:&quot;&quot; }</value>
							<type>range</type>
						</property>
						<property>
							<name>height</name>
							<value>{ &quot;exact&quot;:&quot;&quot;, &quot;min&quot;:&quot;&quot;, &quot;max&quot;:&quot;&quot; }</value>
							<type>range</type>
						</property>
						<property>
							<name>thumbnailWidth</name>
							<value></value>
							<type>int</type>
						</property>
						<property>
							<name>thumbnailHeight</name>
							<value></value>
							<type>int</type>
						</property>
						<property>
							<name>imageManager</name>
							<value>existingimages,uploadimage,existing_images,upload_image</value>
							<type>datasource:image</type>
						</property>
						<property>
							<name>readonly</name>
							<value></value>
							<type>boolean</type>
						</property>
					</properties>
					<constraints>
						<constraint>
							<name>required</name>
							<value><![CDATA[false]]></value>
							<type>boolean</type>
						</constraint>
					</constraints>
				</field>
				<field>
					<type>input</type>
					<id>logo_text_t</id>
					<iceId>hero</iceId>
					<title>Logo Alt Text</title>
					<description></description>
					<defaultValue></defaultValue>
					<help></help>
					<properties>
						<property>
							<name>size</name>
							<value>50</value>
							<type>int</type>
						</property>
						<property>
							<name>maxlength</name>
							<value>50</value>
							<type>int</type>
						</property>
						<property>
							<name>readonly</name>
							<value></value>
							<type>boolean</type>
						</property>
						<property>
							<name>tokenize</name>
							<value>false</value>
							<type>boolean</type>
						</property>
					</properties>
					<constraints>
						<constraint>
							<name>required</name>
							<value><![CDATA[false]]></value>
							<type>boolean</type>
						</constraint>
						<constraint>
							<name>pattern</name>
							<value><![CDATA[]]></value>
							<type>string</type>
						</constraint>
					</constraints>
				</field>
				<field>
					<type>input</type>
					<id>business_name_s</id>
					<iceId>header</iceId>
					<title>Business Name</title>
					<description></description>
					<defaultValue></defaultValue>
					<help></help>
					<properties>
						<property>
							<name>size</name>
							<value>50</value>
							<type>int</type>
						</property>
						<property>
							<name>maxlength</name>
							<value>50</value>
							<type>int</type>
						</property>
						<property>
							<name>readonly</name>
							<value></value>
							<type>boolean</type>
						</property>
						<property>
							<name>tokenize</name>
							<value>false</value>
							<type>boolean</type>
						</property>
					</properties>
					<constraints>
						<constraint>
							<name>required</name>
							<value><![CDATA[true]]></value>
							<type>boolean</type>
						</constraint>
						<constraint>
							<name>pattern</name>
							<value><![CDATA[]]></value>
							<type>string</type>
						</constraint>
					</constraints>
				</field>
			</fields>
		</section>
		<section>
			<title>Social Media Links</title>
			<description></description>
			<defaultOpen>true</defaultOpen>
			<fields>
				<field>
					<type>repeat</type>
					<id>social_media_links_o</id>
					<iceId>hero</iceId>
					<title>Social Media Link</title>
					<description></description>
					<minOccurs>0</minOccurs>
					<maxOccurs>10</maxOccurs>
					<properties>
						<property>
							<name>minOccurs</name>
							<value>0</value>
							<type>string</type>
						</property>
						<property>
							<name>maxOccurs</name>
							<value>10</value>
							<type>string</type>
						</property>
					</properties>
					<fields>
				<field>
					<type>dropdown</type>
					<id>social_media_s</id>
					<iceId>hero</iceId>
					<title>Social Media</title>
					<description></description>
					<defaultValue></defaultValue>
					<help></help>
					<properties>
						<property>
							<name>datasource</name>
							<value>asdf,SocialMediaTypes,SocialMediaTypes,Social Media Types</value>
							<type>datasource:item</type>
						</property>
						<property>
							<name>emptyvalue</name>
							<value></value>
							<type>boolean</type>
						</property>
						<property>
							<name>readonly</name>
							<value></value>
							<type>boolean</type>
						</property>
					</properties>
					<constraints>
						<constraint>
							<name>required</name>
							<value><![CDATA[true]]></value>
							<type>boolean</type>
						</constraint>
					</constraints>
				</field>
				<field>
					<type>input</type>
					<id>url_s</id>
					<iceId>hero</iceId>
					<title>URL</title>
					<description></description>
					<defaultValue></defaultValue>
					<help></help>
					<properties>
						<property>
							<name>size</name>
							<value>50</value>
							<type>int</type>
						</property>
						<property>
							<name>maxlength</name>
							<value>256</value>
							<type>int</type>
						</property>
						<property>
							<name>readonly</name>
							<value></value>
							<type>boolean</type>
						</property>
						<property>
							<name>tokenize</name>
							<value>false</value>
							<type>boolean</type>
						</property>
					</properties>
					<constraints>
						<constraint>
							<name>required</name>
							<value><![CDATA[true]]></value>
							<type>boolean</type>
						</constraint>
						<constraint>
							<name>pattern</name>
							<value><![CDATA[]]></value>
							<type>string</type>
						</constraint>
					</constraints>
				</field>
					</fields>
				</field>
			</fields>
		</section>
	</sections>
	<datasources>				<datasource>
					<type>img-repository-upload</type>
					<id>existing_images</id>
					<title>Existing Images</title>
					<interface>image</interface>
					<properties>
						<property>
							<name>repoPath</name>
							<value>/static-assets/images</value>
								<type>undefined</type>
						</property>
					</properties>
				</datasource>
				<datasource>
					<type>img-desktop-upload</type>
					<id>upload_image</id>
					<title>Upload Images</title>
					<interface>image</interface>
					<properties>
						<property>
							<name>repoPath</name>
							<value>/static-assets/item/images/{yyyy}/{mm}/{dd}/</value>
								<type>undefined</type>
						</property>
					</properties>
				</datasource>
				<datasource>
					<type>key-value-list</type>
					<id>Social Media Types</id>
					<title>Social Media Types</title>
					<interface>item</interface>
					<properties>
						<property>
							<name>dataType</name>
							<value>[{&quot;value&quot;:&quot;value&quot;,&quot;label&quot;:&quot;&quot;,&quot;selected&quot;:false},{&quot;value&quot;:&quot;value_s&quot;,&quot;label&quot;:&quot;String&quot;,&quot;selected&quot;:true},{&quot;value&quot;:&quot;value_i&quot;,&quot;label&quot;:&quot;Integer&quot;,&quot;selected&quot;:false},{&quot;value&quot;:&quot;value_f&quot;,&quot;label&quot;:&quot;Float&quot;,&quot;selected&quot;:false},{&quot;value&quot;:&quot;value_dt&quot;,&quot;label&quot;:&quot;Date&quot;,&quot;selected&quot;:false},{&quot;value&quot;:&quot;value_html&quot;,&quot;label&quot;:&quot;HTML&quot;,&quot;selected&quot;:false}]</value>
								<type>undefined</type>
						</property>
						<property>
							<name>options</name>
							<value>[{&quot;key&quot;:&quot;fa-twitter&quot;,&quot;value&quot;:&quot;Twitter&quot;},{&quot;key&quot;:&quot;fa-facebook&quot;,&quot;value&quot;:&quot;Facebook&quot;},{&quot;key&quot;:&quot;fa-instagram&quot;,&quot;value&quot;:&quot;Instagram&quot;},{&quot;key&quot;:&quot;fa-google-plus&quot;,&quot;value&quot;:&quot;Google+&quot;},{&quot;key&quot;:&quot;fa-snapchat-ghost&quot;,&quot;value&quot;:&quot;Snapchat&quot;},{&quot;key&quot;:&quot;fa-linkedin-square&quot;,&quot;value&quot;:&quot;LinkedIn&quot;},{&quot;key&quot;:&quot;fa-github-alt&quot;,&quot;value&quot;:&quot;GitHub&quot;},{&quot;key&quot;:&quot;fa-stack-overflow&quot;,&quot;value&quot;:&quot;StackOverflow&quot;},{&quot;key&quot;:&quot;fa-medium&quot;,&quot;value&quot;:&quot;Medium&quot;}]</value>
								<type>undefined</type>
						</property>
						<property>
							<name>showkeys</name>
							<value></value>
								<type>undefined</type>
						</property>
					</properties>
				</datasource>
	</datasources>
</form>
